pickle_blosc/__init__.py
pickle_blosc/_core.py
pickle_blosc/_testit.py
pickle_blosc/test/__init__.py
pickle_blosc/test/test_pickle_blosc.py
pickle_blosc-0.1.2.dist-info/LICENSE.md
pickle_blosc-0.1.2.dist-info/METADATA
pickle_blosc-0.1.2.dist-info/WHEEL
pickle_blosc-0.1.2.dist-info/top_level.txt
pickle_blosc-0.1.2.dist-info/zip-safe
pickle_blosc-0.1.2.dist-info/RECORD
