Metadata-Version: 2.1
Name: pickle-blosc
Version: 0.1.2
Summary: Read and write Pickle files using Blosc compression
Home-page: https://github.com/limix/pickle-blosc
Author: Danilo Horta
Author-email: horta@ebi.ac.uk
Maintainer: Danilo Horta
Maintainer-email: horta@ebi.ac.uk
License: MIT
Download-URL: https://github.com/limix/pickle-blosc
Keywords: function,optimisation
Platform: Windows
Platform: MacOS
Platform: Linux
Classifier: Development Status :: 5 - Production/Stable
Classifier: License :: OSI Approved :: MIT License
Classifier: Operating System :: OS Independent
Classifier: Programming Language :: Python
